{
  "timestamp": "2026-02-21T12:08:24.564806+00:00",
  "platform": "linux",
  "hardware": {
    "os": "Linux-6.11.0-1018-azure-x86_64-with-glibc2.39",
    "cpu": "AMD EPYC 7763 64-Core Processor"
  },
  "summary": {
    "total": 3,
    "passed": 2,
    "failed": 0
  },
  "workflows": [
    {
      "name": "pano",
      "status": "skipped",
      "duration_seconds": 0,
      "error": "Not configured for CPU runner",
      "hardware": null
    },
    {
      "name": "sharp_basic",
      "status": "pass",
      "duration_seconds": 224.85,
      "error": null,
      "hardware": {
        "os": "Linux-6.11.0-1018-azure-x86_64-with-glibc2.39",
        "cpu": "AMD EPYC 7763 64-Core Processor"
      },
      "resources": {
        "ram": {
          "peak": 8.97,
          "avg": 6.37
        },
        "total_ram_gb": 15.6,
        "samples": 225
      }
    },
    {
      "name": "sharp_exif",
      "status": "pass",
      "duration_seconds": 206.67,
      "error": null,
      "hardware": {
        "os": "Linux-6.11.0-1018-azure-x86_64-with-glibc2.39",
        "cpu": "AMD EPYC 7763 64-Core Processor"
      },
      "resources": {
        "ram": {
          "peak": 11.19,
          "avg": 8.83
        },
        "total_ram_gb": 15.6,
        "samples": 207
      }
    }
  ]
}